{".class": "MypyFile", "_fullname": "flare.kindling.utils", "is_partial_stub_package": false, "is_stub": false, "names": {".class": "SymbolTable", "Buffer": {".class": "SymbolTableNode", "kind": "Gdef", "node": {".class": "TypeInfo", "_promote": null, "abstract_attributes": [], "bases": ["builtins.object"], "declared_metaclass": null, "defn": {".class": "ClassDef", "fullname": "flare.kindling.utils.Buffer", "name": "Buffer", "type_vars": []}, "flags": [], "fullname": "flare.kindling.utils.Buffer", "metaclass_type": null, "metadata": {}, "module_name": "flare.kindling.utils", "mro": ["flare.kindling.utils.Buffer", "builtins.object"], "names": {".class": "SymbolTable", "__init__": {".class": "SymbolTableNode", "kind": "Mdef", "node": {".class": "FuncDef", "arg_kinds": [0, 0, 0, 0, 1, 1], "arg_names": ["self", "obs_dim", "act_dim", "size", "gamma", "lam"], "flags": [], "fullname": "flare.kindling.utils.Buffer.__init__", "name": "__init__", "type": null}}, "_combined_shape": {".class": "SymbolTableNode", "kind": "Mdef", "node": {".class": "FuncDef", "arg_kinds": [0, 0, 1], "arg_names": ["self", "length", "shape"], "flags": [], "fullname": "flare.kindling.utils.Buffer._combined_shape", "name": "_combined_shape", "type": null}}, "_discount_cumsum": {".class": "SymbolTableNode", "kind": "Mdef", "node": {".class": "FuncDef", "arg_kinds": [0, 0, 0], "arg_names": ["self", "x", "discount"], "flags": [], "fullname": "flare.kindling.utils.Buffer._discount_cumsum", "name": "_discount_cumsum", "type": null}}, "act_buf": {".class": "SymbolTableNode", "implicit": true, "kind": "Mdef", "node": {".class": "Var", "flags": [], "fullname": "flare.kindling.utils.Buffer.act_buf", "name": "act_buf", "type": {".class": "AnyType", "missing_import_name": null, "source_any": null, "type_of_any": 1}}}, "adv_buf": {".class": "SymbolTableNode", "implicit": true, "kind": "Mdef", "node": {".class": "Var", "flags": [], "fullname": "flare.kindling.utils.Buffer.adv_buf", "name": "adv_buf", "type": {".class": "AnyType", "missing_import_name": null, "source_any": null, "type_of_any": 1}}}, "finish_path": {".class": "SymbolTableNode", "kind": "Mdef", "node": {".class": "FuncDef", "arg_kinds": [0, 1], "arg_names": ["self", "last_val"], "flags": [], "fullname": "flare.kindling.utils.Buffer.finish_path", "name": "finish_path", "type": null}}, "gamma": {".class": "SymbolTableNode", "implicit": true, "kind": "Mdef", "node": {".class": "Var", "flags": [], "fullname": "flare.kindling.utils.Buffer.gamma", "name": "gamma", "type": {".class": "AnyType", "missing_import_name": null, "source_any": null, "type_of_any": 1}}}, "get": {".class": "SymbolTableNode", "kind": "Mdef", "node": {".class": "FuncDef", "arg_kinds": [0], "arg_names": ["self"], "flags": [], "fullname": "flare.kindling.utils.Buffer.get", "name": "get", "type": null}}, "lam": {".class": "SymbolTableNode", "implicit": true, "kind": "Mdef", "node": {".class": "Var", "flags": [], "fullname": "flare.kindling.utils.Buffer.lam", "name": "lam", "type": {".class": "AnyType", "missing_import_name": null, "source_any": null, "type_of_any": 1}}}, "logp_buf": {".class": "SymbolTableNode", "implicit": true, "kind": "Mdef", "node": {".class": "Var", "flags": [], "fullname": "flare.kindling.utils.Buffer.logp_buf", "name": "logp_buf", "type": {".class": "AnyType", "missing_import_name": null, "source_any": null, "type_of_any": 1}}}, "max_size": {".class": "SymbolTableNode", "implicit": true, "kind": "Mdef", "node": {".class": "Var", "flags": [], "fullname": "flare.kindling.utils.Buffer.max_size", "name": "max_size", "type": {".class": "AnyType", "missing_import_name": null, "source_any": null, "type_of_any": 1}}}, "obs_buf": {".class": "SymbolTableNode", "implicit": true, "kind": "Mdef", "node": {".class": "Var", "flags": [], "fullname": "flare.kindling.utils.Buffer.obs_buf", "name": "obs_buf", "type": {".class": "AnyType", "missing_import_name": null, "source_any": null, "type_of_any": 1}}}, "path_start_idx": {".class": "SymbolTableNode", "implicit": true, "kind": "Mdef", "node": {".class": "Var", "flags": [], "fullname": "flare.kindling.utils.Buffer.path_start_idx", "name": "path_start_idx", "type": {".class": "AnyType", "missing_import_name": null, "source_any": null, "type_of_any": 1}}}, "ptr": {".class": "SymbolTableNode", "implicit": true, "kind": "Mdef", "node": {".class": "Var", "flags": [], "fullname": "flare.kindling.utils.Buffer.ptr", "name": "ptr", "type": {".class": "AnyType", "missing_import_name": null, "source_any": null, "type_of_any": 1}}}, "ret_buf": {".class": "SymbolTableNode", "implicit": true, "kind": "Mdef", "node": {".class": "Var", "flags": [], "fullname": "flare.kindling.utils.Buffer.ret_buf", "name": "ret_buf", "type": {".class": "AnyType", "missing_import_name": null, "source_any": null, "type_of_any": 1}}}, "rew_buf": {".class": "SymbolTableNode", "implicit": true, "kind": "Mdef", "node": {".class": "Var", "flags": [], "fullname": "flare.kindling.utils.Buffer.rew_buf", "name": "rew_buf", "type": {".class": "AnyType", "missing_import_name": null, "source_any": null, "type_of_any": 1}}}, "store": {".class": "SymbolTableNode", "kind": "Mdef", "node": {".class": "FuncDef", "arg_kinds": [0, 0, 0, 0, 0, 0], "arg_names": ["self", "obs", "act", "rew", "val", "logp"], "flags": [], "fullname": "flare.kindling.utils.Buffer.store", "name": "store", "type": null}}, "val_buf": {".class": "SymbolTableNode", "implicit": true, "kind": "Mdef", "node": {".class": "Var", "flags": [], "fullname": "flare.kindling.utils.Buffer.val_buf", "name": "val_buf", "type": {".class": "AnyType", "missing_import_name": null, "source_any": null, "type_of_any": 1}}}}, "tuple_type": null, "type_vars": [], "typeddict_type": null}}, "F": {".class": "SymbolTableNode", "cross_ref": "torch.nn.functional", "kind": "Gdef"}, "NetworkUtils": {".class": "SymbolTableNode", "kind": "Gdef", "node": {".class": "TypeInfo", "_promote": null, "abstract_attributes": [], "bases": ["builtins.object"], "declared_metaclass": null, "defn": {".class": "ClassDef", "fullname": "flare.kindling.utils.NetworkUtils", "name": "NetworkUtils", "type_vars": []}, "flags": [], "fullname": "flare.kindling.utils.NetworkUtils", "metaclass_type": null, "metadata": {}, "module_name": "flare.kindling.utils", "mro": ["flare.kindling.utils.NetworkUtils", "builtins.object"], "names": {".class": "SymbolTable", "__init__": {".class": "SymbolTableNode", "kind": "Mdef", "node": {".class": "FuncDef", "arg_kinds": [0], "arg_names": ["self"], "flags": [], "fullname": "flare.kindling.utils.NetworkUtils.__init__", "name": "__init__", "type": null}}, "conv2d_output_size": {".class": "SymbolTableNode", "kind": "Mdef", "node": {".class": "FuncDef", "arg_kinds": [0, 0, 0, 0], "arg_names": ["self", "kernel_size", "stride", "sidesize"], "flags": [], "fullname": "flare.kindling.utils.NetworkUtils.conv2d_output_size", "name": "conv2d_output_size", "type": null}}, "squared_error_loss": {".class": "SymbolTableNode", "kind": "Mdef", "node": {".class": "FuncDef", "arg_kinds": [0, 0, 0], "arg_names": ["self", "target", "actual"], "flags": [], "fullname": "flare.kindling.utils.NetworkUtils.squared_error_loss", "name": "squared_error_loss", "type": null}}}, "tuple_type": null, "type_vars": [], "typeddict_type": null}}, "NormalizedActions": {".class": "SymbolTableNode", "kind": "Gdef", "node": {".class": "TypeInfo", "_promote": null, "abstract_attributes": [], "bases": ["builtins.object"], "declared_metaclass": null, "defn": {".class": "ClassDef", "fullname": "flare.kindling.utils.NormalizedActions", "name": "NormalizedActions", "type_vars": []}, "flags": ["fallback_to_any"], "fullname": "flare.kindling.utils.NormalizedActions", "metaclass_type": null, "metadata": {}, "module_name": "flare.kindling.utils", "mro": ["flare.kindling.utils.NormalizedActions", "builtins.object"], "names": {".class": "SymbolTable", "_action": {".class": "SymbolTableNode", "kind": "Mdef", "node": {".class": "FuncDef", "arg_kinds": [0, 0], "arg_names": ["self", "action"], "flags": [], "fullname": "flare.kindling.utils.NormalizedActions._action", "name": "_action", "type": null}}, "_reverse_action": {".class": "SymbolTableNode", "kind": "Mdef", "node": {".class": "FuncDef", "arg_kinds": [0, 0], "arg_names": ["self", "action"], "flags": [], "fullname": "flare.kindling.utils.NormalizedActions._reverse_action", "name": "_reverse_action", "type": null}}}, "tuple_type": null, "type_vars": [], "typeddict_type": null}}, "ReplayBuffer": {".class": "SymbolTableNode", "kind": "Gdef", "node": {".class": "TypeInfo", "_promote": null, "abstract_attributes": [], "bases": ["flare.kindling.utils.Buffer"], "declared_metaclass": null, "defn": {".class": "ClassDef", "fullname": "flare.kindling.utils.ReplayBuffer", "name": "ReplayBuffer", "type_vars": []}, "flags": [], "fullname": "flare.kindling.utils.ReplayBuffer", "metaclass_type": null, "metadata": {}, "module_name": "flare.kindling.utils", "mro": ["flare.kindling.utils.ReplayBuffer", "flare.kindling.utils.Buffer", "builtins.object"], "names": {".class": "SymbolTable", "__init__": {".class": "SymbolTableNode", "kind": "Mdef", "node": {".class": "FuncDef", "arg_kinds": [0, 0, 0, 0], "arg_names": ["self", "obs_dim", "act_dim", "size"], "flags": [], "fullname": "flare.kindling.utils.ReplayBuffer.__init__", "name": "__init__", "type": null}}, "done_buf": {".class": "SymbolTableNode", "implicit": true, "kind": "Mdef", "node": {".class": "Var", "flags": [], "fullname": "flare.kindling.utils.ReplayBuffer.done_buf", "name": "done_buf", "type": {".class": "AnyType", "missing_import_name": null, "source_any": null, "type_of_any": 1}}}, "get_batch": {".class": "SymbolTableNode", "kind": "Mdef", "node": {".class": "FuncDef", "arg_kinds": [0, 1], "arg_names": ["self", "n_sample"], "flags": [], "fullname": "flare.kindling.utils.ReplayBuffer.get_batch", "name": "get_batch", "type": null}}, "obs1_buf": {".class": "SymbolTableNode", "implicit": true, "kind": "Mdef", "node": {".class": "Var", "flags": [], "fullname": "flare.kindling.utils.ReplayBuffer.obs1_buf", "name": "obs1_buf", "type": {".class": "AnyType", "missing_import_name": null, "source_any": null, "type_of_any": 1}}}, "obs2_buf": {".class": "SymbolTableNode", "implicit": true, "kind": "Mdef", "node": {".class": "Var", "flags": [], "fullname": "flare.kindling.utils.ReplayBuffer.obs2_buf", "name": "obs2_buf", "type": {".class": "AnyType", "missing_import_name": null, "source_any": null, "type_of_any": 1}}}, "size": {".class": "SymbolTableNode", "implicit": true, "kind": "Mdef", "node": {".class": "Var", "flags": [], "fullname": "flare.kindling.utils.ReplayBuffer.size", "name": "size", "type": {".class": "AnyType", "missing_import_name": null, "source_any": null, "type_of_any": 1}}}, "store": {".class": "SymbolTableNode", "kind": "Mdef", "node": {".class": "FuncDef", "arg_kinds": [0, 0, 0, 0, 0, 0], "arg_names": ["self", "obs", "act", "rew", "next_obs", "done"], "flags": [], "fullname": "flare.kindling.utils.ReplayBuffer.store", "name": "store", "type": null}}}, "tuple_type": null, "type_vars": [], "typeddict_type": null}}, "__doc__": {".class": "SymbolTableNode", "kind": "Gdef", "node": {".class": "Var", "flags": ["is_ready"], "fullname": "flare.kindling.utils.__doc__", "name": "__doc__", "type": "builtins.str"}}, "__file__": {".class": "SymbolTableNode", "kind": "Gdef", "node": {".class": "Var", "flags": ["is_ready"], "fullname": "flare.kindling.utils.__file__", "name": "__file__", "type": "builtins.str"}}, "__name__": {".class": "SymbolTableNode", "kind": "Gdef", "node": {".class": "Var", "flags": ["is_ready"], "fullname": "flare.kindling.utils.__name__", "name": "__name__", "type": "builtins.str"}}, "__package__": {".class": "SymbolTableNode", "kind": "Gdef", "node": {".class": "Var", "flags": ["is_ready"], "fullname": "flare.kindling.utils.__package__", "name": "__package__", "type": "builtins.str"}}, "animation": {".class": "SymbolTableNode", "kind": "Gdef", "node": {".class": "Var", "flags": ["is_suppressed_import", "is_ready"], "fullname": "flare.kindling.utils.animation", "name": "animation", "type": {".class": "AnyType", "missing_import_name": "flare.kindling.utils.animation", "source_any": null, "type_of_any": 3}}}, "gaussian_likelihood": {".class": "SymbolTableNode", "kind": "Gdef", "node": {".class": "FuncDef", "arg_kinds": [0, 0, 0], "arg_names": ["x", "mu", "log_std"], "flags": [], "fullname": "flare.kindling.utils.gaussian_likelihood", "name": "gaussian_likelihood", "type": null}}, "gym": {".class": "SymbolTableNode", "kind": "Gdef", "node": {".class": "Var", "flags": ["is_suppressed_import", "is_ready"], "fullname": "flare.kindling.utils.gym", "name": "gym", "type": {".class": "AnyType", "missing_import_name": "flare.kindling.utils.gym", "source_any": null, "type_of_any": 3}}}, "math": {".class": "SymbolTableNode", "cross_ref": "math", "kind": "Gdef"}, "nn": {".class": "SymbolTableNode", "cross_ref": "torch.nn", "kind": "Gdef"}, "np": {".class": "SymbolTableNode", "kind": "Gdef", "node": {".class": "Var", "flags": ["is_suppressed_import", "is_ready"], "fullname": "flare.kindling.utils.np", "name": "np", "type": {".class": "AnyType", "missing_import_name": "flare.kindling.utils.np", "source_any": null, "type_of_any": 3}}}, "optim": {".class": "SymbolTableNode", "cross_ref": "torch.optim", "kind": "Gdef"}, "plt": {".class": "SymbolTableNode", "kind": "Gdef", "node": {".class": "Var", "flags": ["is_suppressed_import", "is_ready"], "fullname": "flare.kindling.utils.plt", "name": "plt", "type": {".class": "AnyType", "missing_import_name": "flare.kindling.utils.plt", "source_any": null, "type_of_any": 3}}}, "save_frames_as_gif": {".class": "SymbolTableNode", "kind": "Gdef", "node": {".class": "FuncDef", "arg_kinds": [0, 1], "arg_names": ["frames", "filename"], "flags": [], "fullname": "flare.kindling.utils.save_frames_as_gif", "name": "save_frames_as_gif", "type": null}}, "scipy": {".class": "SymbolTableNode", "kind": "Gdef", "node": {".class": "Var", "flags": ["is_suppressed_import", "is_ready"], "fullname": "flare.kindling.utils.scipy", "name": "scipy", "type": {".class": "AnyType", "missing_import_name": "flare.kindling.utils.scipy", "source_any": null, "type_of_any": 3}}}, "signal": {".class": "SymbolTableNode", "kind": "Gdef", "node": {".class": "Var", "flags": ["is_suppressed_import", "is_ready"], "fullname": "flare.kindling.utils.signal", "name": "signal", "type": {".class": "AnyType", "missing_import_name": "flare.kindling.utils.signal", "source_any": null, "type_of_any": 3}}}, "torch": {".class": "SymbolTableNode", "cross_ref": "torch", "kind": "Gdef"}, "wrappers": {".class": "SymbolTableNode", "kind": "Gdef", "node": {".class": "Var", "flags": ["is_suppressed_import", "is_ready"], "fullname": "flare.kindling.utils.wrappers", "name": "wrappers", "type": {".class": "AnyType", "missing_import_name": "flare.kindling.utils.wrappers", "source_any": null, "type_of_any": 3}}}}, "path": "/Users/pettit8/Documents/git/flare/flare/kindling/utils.py"}